<annotation>
  <folder>C:/Users/Dan/Desktop/NASA RESEARCH/CRS_Master_2000/CRS_1600_TRAIN</folder>
  <filename>000660.jpg</filename>
  <segmented>0</segmented>
  <size>
    <width>4048</width>
    <height>3036</height>
    <depth>3</depth>
  </size>
  <object>
    <name>cross_recessed_screw</name>
    <pose>Unspecified</pose>
    <truncated>0</truncated>
    <difficult>0</difficult>
    <bndbox>
      <xmin>95</xmin>
      <ymin>707</ymin>
      <xmax>282</xmax>
      <ymax>898</ymax>
    </bndbox>
  </object>
  <object>
    <name>cross_recessed_screw</name>
    <pose>Unspecified</pose>
    <truncated>0</truncated>
    <difficult>0</difficult>
    <bndbox>
      <xmin>1318</xmin>
      <ymin>2706</ymin>
      <xmax>1521</xmax>
      <ymax>2901</ymax>
    </bndbox>
  </object>
  <object>
    <name>cross_recessed_screw</name>
    <pose>Unspecified</pose>
    <truncated>0</truncated>
    <difficult>0</difficult>
    <bndbox>
      <xmin>1845</xmin>
      <ymin>2801</ymin>
      <xmax>2015</xmax>
      <ymax>2984</ymax>
    </bndbox>
  </object>
  <object>
    <name>cross_recessed_screw</name>
    <pose>Unspecified</pose>
    <truncated>0</truncated>
    <difficult>0</difficult>
    <bndbox>
      <xmin>3694</xmin>
      <ymin>1197</ymin>
      <xmax>3897</xmax>
      <ymax>1412</ymax>
    </bndbox>
  </object>
</annotation>
