<annotation>
  <folder>C:/Users/Dan/Desktop/NASA RESEARCH/CRS_Master_2000/CRS_1600_TRAIN</folder>
  <filename>001267.jpg</filename>
  <segmented>0</segmented>
  <size>
    <width>3036</width>
    <height>4048</height>
    <depth>3</depth>
  </size>
  <object>
    <name>cross_recessed_screw</name>
    <pose>Unspecified</pose>
    <truncated>0</truncated>
    <difficult>0</difficult>
    <bndbox>
      <xmin>1445</xmin>
      <ymin>1624</ymin>
      <xmax>1650</xmax>
      <ymax>1817</ymax>
    </bndbox>
  </object>
  <object>
    <name>cross_recessed_screw</name>
    <pose>Unspecified</pose>
    <truncated>0</truncated>
    <difficult>0</difficult>
    <bndbox>
      <xmin>1810</xmin>
      <ymin>2696</ymin>
      <xmax>1998</xmax>
      <ymax>2889</ymax>
    </bndbox>
  </object>
</annotation>
