<annotation>
  <folder>C:/Users/Dan/Desktop/NASA RESEARCH/CRS_Master_2000/CRS_1600_TRAIN</folder>
  <filename>001556.jpg</filename>
  <segmented>0</segmented>
  <size>
    <width>3036</width>
    <height>4048</height>
    <depth>3</depth>
  </size>
  <object>
    <name>cross_recessed_screw</name>
    <pose>Unspecified</pose>
    <truncated>0</truncated>
    <difficult>0</difficult>
    <bndbox>
      <xmin>1550</xmin>
      <ymin>673</ymin>
      <xmax>1710</xmax>
      <ymax>833</ymax>
    </bndbox>
  </object>
  <object>
    <name>cross_recessed_screw</name>
    <pose>Unspecified</pose>
    <truncated>0</truncated>
    <difficult>0</difficult>
    <bndbox>
      <xmin>1108</xmin>
      <ymin>264</ymin>
      <xmax>1241</xmax>
      <ymax>418</ymax>
    </bndbox>
  </object>
  <object>
    <name>cross_recessed_screw</name>
    <pose>Unspecified</pose>
    <truncated>0</truncated>
    <difficult>0</difficult>
    <bndbox>
      <xmin>411</xmin>
      <ymin>1010</ymin>
      <xmax>550</xmax>
      <ymax>1143</ymax>
    </bndbox>
  </object>
  <object>
    <name>cross_recessed_screw</name>
    <pose>Unspecified</pose>
    <truncated>0</truncated>
    <difficult>0</difficult>
    <bndbox>
      <xmin>113</xmin>
      <ymin>1436</ymin>
      <xmax>290</xmax>
      <ymax>1607</ymax>
    </bndbox>
  </object>
</annotation>
